skunkbooth/__init__.py
skunkbooth/data/ComicMono.ttf
skunkbooth/data/FiraCode.ttf
skunkbooth/data/Hack.ttf
skunkbooth/data/Monoid.ttf
skunkbooth/data/NotoMono.ttf
skunkbooth/data/__init__.py
skunkbooth/data/constants.py
skunkbooth/data/defaults.py
skunkbooth/filters/__init__.py
skunkbooth/filters/alphabet.py
skunkbooth/filters/arrows.py
skunkbooth/filters/copyright.py
skunkbooth/filters/dollars.py
skunkbooth/filters/flip.py
skunkbooth/filters/grid.py
skunkbooth/filters/hash_tag.py
skunkbooth/filters/invert.py
skunkbooth/filters/matrix.py
skunkbooth/filters/question_mark.py
skunkbooth/filters/rupees.py
skunkbooth/filters/shovels.py
skunkbooth/filters/star_stripes.py
skunkbooth/filters/stars.py
skunkbooth/main.py
skunkbooth/utils/CamReader.py
skunkbooth/utils/__init__.py
skunkbooth/utils/asciiGen.py
skunkbooth/utils/fileIO.py
skunkbooth/utils/filterManager.py
skunkbooth/utils/frames.py
skunkbooth/utils/logger.py
skunkbooth/utils/videoManager.py
skunkbooth/utils/webcam.py
skunkbooth-0.3.dist-info/entry_points.txt
skunkbooth-0.3.dist-info/LICENSE
skunkbooth-0.3.dist-info/WHEEL
skunkbooth-0.3.dist-info/METADATA
skunkbooth-0.3.dist-info/RECORD
