Metadata-Version: 2.1
Name: skunkbooth
Version: 0.3
Summary: A camera app in terminal. One more reason to stay inside terminal.
Home-page: https://github.com/Davidy22/scholarlySkunkJam
License: MIT
Author: Davidy22, dhananjaylatkar, Trisanu-007, shriram1998 and garuna-m6
Requires-Python: >=3.8,<4.0
Classifier: License :: OSI Approved :: MIT License
Classifier: Programming Language :: Python :: 3
Classifier: Programming Language :: Python :: 3.8
Classifier: Programming Language :: Python :: 3.9
Requires-Dist: asciimatics (>=1.13,<2.0)
Requires-Dist: opencv-python (>=4.5,<5.0)
Project-URL: Repository, https://github.com/Davidy22/scholarlySkunkJam
